crumbs/disk-usage/disk-usage.sh
crumbs/disk-usage/info.txt
crumbs/git-log/git-log.sh
crumbs/git-log/info.txt
crumbs/git-status/git-status.sh
crumbs/git-status/info.txt
crumbs/process-list/info.txt
crumbs/process-list/process-list.sh
crumbs/recent-files/info.txt
crumbs/recent-files/recent-files.sh
crumbs/system-health/info.txt
crumbs/system-health/system-health.sh
ducky/__init__.py
ducky/config.py
ducky/ducky.py
examples/POLLING_USER_GUIDE.md
examples/mock-logs/info.txt
examples/mock-logs/mock-logs.sh
rubber_ducky-1.5.0.dist-info/licenses/LICENSE
rubber_ducky-1.5.0.dist-info/METADATA
rubber_ducky-1.5.0.dist-info/WHEEL
rubber_ducky-1.5.0.dist-info/entry_points.txt
rubber_ducky-1.5.0.dist-info/top_level.txt
rubber_ducky-1.5.0.dist-info/RECORD
