Metadata-Version: 2.4
Name: rubber-ducky
Version: 1.5.0
Summary: Quick CLI do-it-all tool. Use natural language to spit out bash commands
Requires-Python: >=3.10
License-File: LICENSE
Requires-Dist: colorama>=0.4.6
Requires-Dist: fastapi>=0.115.11
Requires-Dist: ollama>=0.6.0
Requires-Dist: openai>=1.60.2
Requires-Dist: prompt-toolkit>=3.0.48
Requires-Dist: rich>=13.9.4
Requires-Dist: termcolor>=2.5.0
Dynamic: license-file
